{
  "paused": false,
  "pause_reason": "",
  "rate_limit_reset_at": null,
  "last_run_started_at": "2026-07-21T19:00:01.202916Z",
  "input_file": "/Users/not/projects/devs/opensource/x-kit/data/vibeloft_twitter_account_stats.json",
  "account_count": 73,
  "next_index": 16,
  "updated_at": "2026-07-21T19:21:24.060554Z",
  "current_handle": null,
  "last_run_finished_at": "2026-07-21T18:45:39.006180Z",
  "last_completed_handle": "leexinq",
  "last_completed_at": "2026-07-21T19:21:24.060410Z",
  "rate_limit_reset_at_local": "2026-07-22T00:00:11+08:00"
}
